[
  {
    "name": "赤岩　　善生",
    "lane": 2,
    "note": "外マイ",
    "mark": "△"
  },
  {
    "name": "浦田　　信義",
    "lane": 1,
    "note": "ターンマークに寄る→差され",
    "mark": "△"
  },
  {
    "name": "鈴木　　章司",
    "lane": 2,
    "note": "外マイ",
    "mark": "△"
  },
  {
    "name": "寺田　　　祥",
    "lane": 1,
    "note": "ターン漏らす→2,3,5差され、捲り差され",
    "mark": "△"
  },
  {
    "name": "大久保　佑香",
    "lane": 3,
    "note": "後手捲り差し→2残し",
    "mark": "△"
  },
  {
    "name": "田添　　康介",
    "lane": 5,
    "note": "外マイ流れ",
    "mark": "△"
  },
  {
    "name": "長谷川　晴哉",
    "lane": 1,
    "note": "出遅れ→捲られ",
    "mark": "△"
  },
  {
    "name": "松本　　博昭",
    "lane": 3,
    "note": "ツケマイ○",
    "mark": "◯"
  },
  {
    "name": "橋本　　久和",
    "lane": 1,
    "note": "ST△→捲られ",
    "mark": "△"
  },
  {
    "name": "豊田　　　結",
    "lane": 2,
    "note": "ジカマ○",
    "mark": "◯"
  },
  {
    "name": "平山　　智加",
    "lane": 1,
    "note": "差され→1=2",
    "mark": "△"
  },
  {
    "name": "乙津　　康志",
    "lane": 1,
    "note": "出遅れ捲られor差され",
    "mark": "△"
  },
  {
    "name": "竹井　　貴史",
    "lane": 5,
    "note": "2-4捲り差し〇",
    "mark": "◯"
  },
  {
    "name": "深川　　和仁",
    "lane": 3,
    "note": "捲り差し〇→1=3",
    "mark": "◯"
  },
  {
    "name": "後藤　　　浩",
    "lane": 2,
    "note": "差し流れ→1-3",
    "mark": "△"
  },
  {
    "name": "久田　　　武",
    "lane": 2,
    "note": "外マイ流れ→1-4",
    "mark": "△"
  },
  {
    "name": "山崎　小葉音",
    "lane": 4,
    "note": "差し流れ→5△　※2か3が凹んで握れるときは残す可能性あり",
    "mark": "△"
  }
]